scopus_of_science/__init__.py
scopus_of_science/constants.py
scopus_of_science/file_handler.py
scopus_of_science/sos.py
tests/__init__.py
tests/prova.py
tests/test_constants.py
tests/test_file_handler.py
tests/test_sos.py
scopus_of_science-0.0.2.dist-info/LICENSE
scopus_of_science-0.0.2.dist-info/METADATA
scopus_of_science-0.0.2.dist-info/WHEEL
scopus_of_science-0.0.2.dist-info/top_level.txt
scopus_of_science-0.0.2.dist-info/RECORD
