Metadata-Version: 2.1
Name: scopus-of-science
Version: 0.0.2
Summary: Merge Scopus and WoS databases in Scopus csv format
Home-page: https://github.com/albesibbe/scopus_of_science
Author: Alberto Silvestri
Author-email: albertosilvestri@me.com
License: UNKNOWN
Keywords: Scopus,Web of Science,wos
Platform: UNKNOWN
Classifier: Programming Language :: Python :: 3
Classifier: License :: OSI Approved :: GNU General Public License v3 (GPLv3)
Classifier: Operating System :: OS Independent
Requires-Dist: pandas
